Metadata-Version: 1.0
Name: getpass2
Version: 1.0.2
Summary: A better lib compared with standard "getpass" in Python, easier and simpler to use.
Home-page: https://github.com/guoruibiao/getpass2
Author: UNKNOWN
Author-email: UNKNOWN
License: MIT
Platform: UNKNOWN
